qpsolvers/__init__.py
qpsolvers/_internals.py
qpsolvers/active_set.py
qpsolvers/exceptions.py
qpsolvers/problem.py
qpsolvers/problems.py
qpsolvers/py.typed
qpsolvers/solution.py
qpsolvers/solve_ls.py
qpsolvers/solve_problem.py
qpsolvers/solve_qp.py
qpsolvers/solve_unconstrained.py
qpsolvers/utils.py
qpsolvers/warnings.py
qpsolvers/conversions/__init__.py
qpsolvers/conversions/combine_linear_box_inequalities.py
qpsolvers/conversions/ensure_sparse_matrices.py
qpsolvers/conversions/linear_from_box_inequalities.py
qpsolvers/conversions/socp_from_qp.py
qpsolvers/conversions/split_dual_linear_box.py
qpsolvers/solvers/__init__.py
qpsolvers/solvers/clarabel_.py
qpsolvers/solvers/cvxopt_.py
qpsolvers/solvers/daqp_.py
qpsolvers/solvers/ecos_.py
qpsolvers/solvers/gurobi_.py
qpsolvers/solvers/highs_.py
qpsolvers/solvers/hpipm_.py
qpsolvers/solvers/jaxopt_osqp_.py
qpsolvers/solvers/kvxopt_.py
qpsolvers/solvers/mosek_.py
qpsolvers/solvers/osqp_.py
qpsolvers/solvers/piqp_.py
qpsolvers/solvers/proxqp_.py
qpsolvers/solvers/qpalm_.py
qpsolvers/solvers/qpax_.py
qpsolvers/solvers/qpoases_.py
qpsolvers/solvers/qpswift_.py
qpsolvers/solvers/quadprog_.py
qpsolvers/solvers/scs_.py
qpsolvers/solvers/sip_.py
qpsolvers/unsupported/__init__.py
qpsolvers/unsupported/nppro_.py
qpsolvers-4.8.1.dist-info/licenses/LICENSE
qpsolvers-4.8.1.dist-info/WHEEL
qpsolvers-4.8.1.dist-info/METADATA
qpsolvers-4.8.1.dist-info/RECORD
