Metadata-Version: 2.4
Name: qpsolvers
Version: 4.8.1
Summary: Quadratic programming solvers in Python with a unified API.
Keywords: quadratic programming,solver,numerical optimization
Author-email: Stéphane Caron <stephane.caron@normalesup.org>
Maintainer-email: Stéphane Caron <stephane.caron@normalesup.org>
Requires-Python: >=3.8
Classifier: Development Status :: 5 - Production/Stable
Classifier: Intended Audience :: Developers
Classifier: Intended Audience :: Science/Research
Classifier: License :: OSI Approved :: GNU Lesser General Public License v3 (LGPLv3)
Classifier: Operating System :: OS Independent
Classifier: Programming Language :: Python :: 3.9
Classifier: Programming Language :: Python :: 3.10
Classifier: Programming Language :: Python :: 3.11
Classifier: Programming Language :: Python :: 3.12
Classifier: Topic :: Scientific/Engineering :: Mathematics
License-File: LICENSE
Requires-Dist: numpy >=1.15.4
Requires-Dist: scipy >=1.2.0
Requires-Dist: clarabel >=0.4.1 ; extra == "clarabel"
Requires-Dist: cvxopt >=1.2.6 ; extra == "cvxopt"
Requires-Dist: daqp >=0.5.1 ; extra == "daqp"
Requires-Dist: ecos >=2.0.8 ; extra == "ecos"
Requires-Dist: gurobipy >=9.5.2 ; extra == "gurobi"
Requires-Dist: highspy >=1.1.2.dev3 ; extra == "highs"
Requires-Dist: jaxopt >=0.8.3 ; extra == "jaxopt"
Requires-Dist: kvxopt >=1.3.2 ; extra == "kvxopt"
Requires-Dist: cvxopt >=1.2.6 ; extra == "mosek"
Requires-Dist: mosek >=10.0.40 ; extra == "mosek"
Requires-Dist: qpsolvers[clarabel, cvxopt, daqp, ecos, highs, jaxopt, osqp, piqp, proxqp, qpalm, quadprog, scs, sip, qpax] ; extra == "open-source-solvers"
Requires-Dist: osqp >=0.6.2 ; extra == "osqp"
Requires-Dist: piqp >=0.2.2 ; extra == "piqp"
Requires-Dist: proxsuite >=0.2.9 ; extra == "proxqp"
Requires-Dist: qpalm >=1.2.1 ; extra == "qpalm"
Requires-Dist: qpax>=0.0.9 ; extra == "qpax"
Requires-Dist: quadprog >=0.1.11 ; extra == "quadprog"
Requires-Dist: scs >=3.2.0 ; extra == "scs"
Requires-Dist: sip-python >=0.0.2 ; extra == "sip"
Requires-Dist: qpsolvers[cvxopt, daqp, ecos, highs, piqp, proxqp, qpalm, sip] ; extra == "wheels-only"
Project-URL: Changelog, https://github.com/qpsolvers/qpsolvers/blob/main/CHANGELOG.md
Project-URL: Documentation, https://qpsolvers.github.io/qpsolvers/
Project-URL: Homepage, https://github.com/qpsolvers/qpsolvers
Project-URL: Source, https://github.com/qpsolvers/qpsolvers
Project-URL: Tracker, https://github.com/qpsolvers/qpsolvers/issues
Provides-Extra: clarabel
Provides-Extra: cvxopt
Provides-Extra: daqp
Provides-Extra: ecos
Provides-Extra: gurobi
Provides-Extra: highs
Provides-Extra: jaxopt
Provides-Extra: kvxopt
Provides-Extra: mosek
Provides-Extra: open-source-solvers
Provides-Extra: osqp
Provides-Extra: piqp
Provides-Extra: proxqp
Provides-Extra: qpalm
Provides-Extra: qpax
Provides-Extra: quadprog
Provides-Extra: scs
Provides-Extra: sip
Provides-Extra: wheels-only
